lib/mkciud/__init__.py
lib/mkciud/__main__.py
lib/mkciud/_internal.py
mkciud/__init__.py
mkciud/__main__.py
mkciud/_internal.py
mkciud-1.0.1.dist-info/LICENSE
mkciud-1.0.1.dist-info/METADATA
mkciud-1.0.1.dist-info/WHEEL
mkciud-1.0.1.dist-info/entry_points.txt
mkciud-1.0.1.dist-info/top_level.txt
mkciud-1.0.1.dist-info/RECORD
